TrackPal-1.2.0.dist-info/METADATA
TrackPal-1.2.0.dist-info/RECORD
TrackPal-1.2.0.dist-info/WHEEL
TrackPal-1.2.0.dist-info/top_level.txt
trackpal/__blank__.py
trackpal/__init__.py
trackpal/drift.py
trackpal/features.py
trackpal/fit.py
trackpal/msd.py
trackpal/read.py
trackpal/simulate.py
trackpal/utils.py
trackpal/velocity.py
trackpal/version.py
trackpal/visu.py
