Metadata-Version: 2.1
Name: TrackPal
Version: 1.2.0
Summary: TrackPal: Tracking Python AnaLyzer
Home-page: https://git.ist.ac.at/csommer/trackpal
Author: Christoph Sommer
Author-email: christoph.sommer23@gmail.com
License: BSD
Platform: UNKNOWN
Classifier: Development Status :: 4 - Beta
Classifier: Programming Language :: Python :: 3
Classifier: License :: OSI Approved :: BSD License
Requires-Dist: numpy
Requires-Dist: pandas (>=1.0.4)
Requires-Dist: scikit-image
Requires-Dist: scikit-learn (==0.21.1)
Requires-Dist: tifffile
Requires-Dist: tqdm
Requires-Dist: scipy
Requires-Dist: statsmodels
Requires-Dist: matplotlib
Requires-Dist: rdp
Requires-Dist: tqdm
Requires-Dist: pingouin
